zephyr/__init__.py
zephyr/scale/__init__.py
zephyr/scale/scale.py
zephyr/scale/zephyr_session.py
zephyr/scale/cloud/__init__.py
zephyr/scale/cloud/cloud_api.py
zephyr/scale/cloud/endpoints/__init__.py
zephyr/scale/cloud/endpoints/endpoints.py
zephyr/scale/cloud/endpoints/paths.py
zephyr/scale/server/__init__.py
zephyr/scale/server/server_api.py
zephyr/scale/server/server_defaults.py
zephyr/scale/server/endpoints/__init__.py
zephyr/scale/server/endpoints/endpoints.py
zephyr/scale/server/endpoints/paths.py
zephyr/utils/__init__.py
zephyr/utils/common.py
zephyr_python_api-0.1.0.dist-info/LICENSE
zephyr_python_api-0.1.0.dist-info/METADATA
zephyr_python_api-0.1.0.dist-info/WHEEL
zephyr_python_api-0.1.0.dist-info/top_level.txt
zephyr_python_api-0.1.0.dist-info/RECORD
