Metadata-Version: 2.1
Name: zephyr-python-api
Version: 0.1.0
Summary: Zephyr (TM4J) Python REST API wrapper
Home-page: https://github.com/nassauwinter/zephyr-python-api
Author: Petr Sharapenko
Author-email: nassauwinter@gmail.com
Project-URL: Bug Tracker, https://github.com/nassauwinter/zephyr-python-api/issues
Classifier: Programming Language :: Python :: 3.6
Classifier: Programming Language :: Python :: 3.7
Classifier: Programming Language :: Python :: 3.8
Classifier: Programming Language :: Python :: 3.9
Classifier: Programming Language :: Python :: 3.10
Classifier: Programming Language :: Python :: 3.11
Classifier: Programming Language :: Python :: 3.12
Classifier: License :: OSI Approved :: Apache Software License
Classifier: Operating System :: OS Independent
Requires-Python: >=3.6
License-File: LICENSE
Requires-Dist: requests
